MANIFEST.in
README
setup.py
bw_sphinxtheme/__init__.py
bw_sphinxtheme/__init__.pyc
bw_sphinxtheme.egg-info/PKG-INFO
bw_sphinxtheme.egg-info/SOURCES.txt
bw_sphinxtheme.egg-info/dependency_links.txt
bw_sphinxtheme.egg-info/not-zip-safe
bw_sphinxtheme.egg-info/top_level.txt
bw_sphinxtheme/themes/bw/defindex.html
bw_sphinxtheme/themes/bw/domainindex.html
bw_sphinxtheme/themes/bw/genindex-single.html
bw_sphinxtheme/themes/bw/genindex-split.html
bw_sphinxtheme/themes/bw/genindex.html
bw_sphinxtheme/themes/bw/globaltoc.html
bw_sphinxtheme/themes/bw/layout.html
bw_sphinxtheme/themes/bw/localtoc.html
bw_sphinxtheme/themes/bw/opensearch.xml
bw_sphinxtheme/themes/bw/page.html
bw_sphinxtheme/themes/bw/relations.html
bw_sphinxtheme/themes/bw/search.html
bw_sphinxtheme/themes/bw/searchbox.html
bw_sphinxtheme/themes/bw/searchresults.html
bw_sphinxtheme/themes/bw/sourcelink.html
bw_sphinxtheme/themes/bw/theme.conf
bw_sphinxtheme/themes/bw/changes/frameset.html
bw_sphinxtheme/themes/bw/changes/rstsource.html
bw_sphinxtheme/themes/bw/changes/versionchanges.html
bw_sphinxtheme/themes/bw/static/ajax-loader.gif
bw_sphinxtheme/themes/bw/static/basic.css_t
bw_sphinxtheme/themes/bw/static/comment-bright.png
bw_sphinxtheme/themes/bw/static/comment-close.png
bw_sphinxtheme/themes/bw/static/comment.png
bw_sphinxtheme/themes/bw/static/doctools.js
bw_sphinxtheme/themes/bw/static/down-pressed.png
bw_sphinxtheme/themes/bw/static/down.png
bw_sphinxtheme/themes/bw/static/file.png
bw_sphinxtheme/themes/bw/static/jquery.js
bw_sphinxtheme/themes/bw/static/minus.png
bw_sphinxtheme/themes/bw/static/plus.png
bw_sphinxtheme/themes/bw/static/searchtools.js_t
bw_sphinxtheme/themes/bw/static/underscore.js
bw_sphinxtheme/themes/bw/static/up-pressed.png
bw_sphinxtheme/themes/bw/static/up.png
bw_sphinxtheme/themes/bw/static/websupport.js