Metadata-Version: 1.0
Name: bw-sphinxtheme
Version: 0.1.2
Summary: Minimalistic sphinx theme in black and white colours
Home-page: http://pypi.python.org/pypi/bw_sphinxtheme
Author: Andrey Popp
Author-email: 8mayday@gmail.com
License: BSD3
Platform: UNKNOWN
